.test-requires
LICENSE
MANIFEST.in
README.rst
setup.py
test_urltree.py
tox.ini
urltree.py
urltree.egg-info/PKG-INFO
urltree.egg-info/SOURCES.txt
urltree.egg-info/dependency_links.txt
urltree.egg-info/top_level.txt