Metadata-Version: 1.0
Name: urltree
Version: 0.1.0
Summary: URLTree URL Router
Home-page: https://github.com/klmitch/urltree
Author: Kevin L. Mitchell
Author-email: kevin.mitchell@rackspace.com
License: Apache License (2.0)
Platform: UNKNOWN
Classifier: Development Status :: 4 - Beta
Classifier: Environment :: Web Environment
Classifier: Intended Audience :: Developers
Classifier: License :: OSI Approved :: Apache Software License
Classifier: Programming Language :: Python
Classifier: Topic :: Internet :: WWW/HTTP
